osbot_docker/__init__.py
osbot_docker/apis/API_Docker.py
osbot_docker/apis/Docker_Container.py
osbot_docker/apis/Docker_Image.py
osbot_docker/apis/__init__.py
osbot_docker/helpers/Container__Lambda_Python.py
osbot_docker/helpers/Docker_Lambda__Python.py
osbot_docker/helpers/Yaml.py
osbot_docker/helpers/__init__.py
osbot_docker/version
osbot_docker-0.6.0.dist-info/LICENSE
osbot_docker-0.6.0.dist-info/METADATA
osbot_docker-0.6.0.dist-info/WHEEL
osbot_docker-0.6.0.dist-info/RECORD
